harami/EventArgs.py
harami/EventHandler.py
harami/EventSource.py
harami/Observable.py
harami/Observer.py
harami/__init__.py
harami-0.0.9.dist-info/licenses/LICENSE
harami-0.0.9.dist-info/METADATA
harami-0.0.9.dist-info/WHEEL
harami-0.0.9.dist-info/top_level.txt
harami-0.0.9.dist-info/RECORD
