Metadata-Version: 2.4
Name: harami
Version: 0.0.9
Summary: A lightweight 'Event' and 'Observable' library.
Author-email: Shaun Wilson <mrshaunwilson@msn.com>
Project-URL: Documentation, https://harami.readthedocs.io/
Project-URL: Homepage, https://github.com/wilson0x4d/harami
Project-URL: Repository, https://github.com/wilson0x4d/harami.git
Keywords: event,eventhandler,observable,observer
Classifier: License :: OSI Approved :: MIT License
Classifier: Operating System :: OS Independent
Classifier: Programming Language :: Python :: 3.12
Classifier: Programming Language :: Python :: 3.13
Classifier: Topic :: Software Development :: Libraries :: Python Modules
Classifier: Intended Audience :: Developers
Requires-Python: >=3.12
License-File: LICENSE
Dynamic: license-file
